{
  "appPageId" : "49a9d117-0297-44e8-b92f-dbc02ab7f703",
  "componentName" : "siteforce:sldsOneColLayout",
  "dataProviders" : [ ],
  "id" : "0143e7eb-13a1-4928-ab07-e38de11442ee",
  "label" : "Messages",
  "regions" : [ {
    "components" : [ {
      "componentAttributes" : { },
      "componentName" : "forceChatter:messages",
      "id" : "ca471484-9363-4acb-8e2b-f182c1809a97",
      "renderPriority" : "NEUTRAL",
      "renditionMap" : { },
      "type" : "component"
    } ],
    "id" : "3fbd935d-874a-41a6-8cca-91b866f4d72a",
    "regionName" : "content",
    "type" : "region"
  } ],
  "themeLayoutType" : "Inner",
  "type" : "view",
  "viewType" : "messages"
}